hwapi/__init__.py
hwapi/client.py
hwapi/models.py
hwapi/utils.py
hwapi-0.1.3.dist-info/LICENSE
hwapi-0.1.3.dist-info/METADATA
hwapi-0.1.3.dist-info/WHEEL
hwapi-0.1.3.dist-info/top_level.txt
hwapi-0.1.3.dist-info/RECORD
