Metadata-Version: 2.1
Name: hwapi
Version: 0.1.3
Summary: Happy Wheels API Wrapper
Home-page: https://github.com/kittenswolf/hwapi
Author: kittenswolf
License: UNKNOWN
Project-URL: Bug Reports, https://github.com/kittenswolf/hwapi/issues
Project-URL: Source, https://github.com/kittenswolf/hwapi/
Platform: UNKNOWN
Requires-Python: >=3.6.0
Requires-Dist: aiohttp (>3)
Requires-Dist: beautifulsoup4 (<5,>4)
Requires-Dist: cachetools
Requires-Dist: xmltodict
